kedro_datasets/__init__.py
kedro_datasets/_typing.py
kedro_datasets/_utils/__init__.py
kedro_datasets/_utils/connection_mixin.py
kedro_datasets/_utils/databricks_utils.py
kedro_datasets/_utils/spark_utils.py
kedro_datasets/api/__init__.py
kedro_datasets/api/api_dataset.py
kedro_datasets/biosequence/__init__.py
kedro_datasets/biosequence/biosequence_dataset.py
kedro_datasets/dask/__init__.py
kedro_datasets/dask/csv_dataset.py
kedro_datasets/dask/parquet_dataset.py
kedro_datasets/databricks/__init__.py
kedro_datasets/databricks/_base_table_dataset.py
kedro_datasets/databricks/managed_table_dataset.py
kedro_datasets/email/__init__.py
kedro_datasets/email/message_dataset.py
kedro_datasets/geopandas/__init__.py
kedro_datasets/geopandas/generic_dataset.py
kedro_datasets/holoviews/__init__.py
kedro_datasets/holoviews/holoviews_writer.py
kedro_datasets/huggingface/__init__.py
kedro_datasets/huggingface/hugging_face_dataset.py
kedro_datasets/huggingface/transformer_pipeline_dataset.py
kedro_datasets/ibis/__init__.py
kedro_datasets/ibis/file_dataset.py
kedro_datasets/ibis/table_dataset.py
kedro_datasets/json/__init__.py
kedro_datasets/json/json_dataset.py
kedro_datasets/langchain/__init__.py
kedro_datasets/langchain/chat_anthropic_dataset.py
kedro_datasets/langchain/chat_cohere_dataset.py
kedro_datasets/langchain/chat_openai_dataset.py
kedro_datasets/langchain/openai_embeddings_dataset.py
kedro_datasets/matlab/__init__.py
kedro_datasets/matlab/matlab_dataset.py
kedro_datasets/matplotlib/__init__.py
kedro_datasets/matplotlib/matplotlib_dataset.py
kedro_datasets/networkx/__init__.py
kedro_datasets/networkx/gml_dataset.py
kedro_datasets/networkx/graphml_dataset.py
kedro_datasets/networkx/json_dataset.py
kedro_datasets/openxml/__init__.py
kedro_datasets/openxml/docx_dataset.py
kedro_datasets/openxml/pptx_dataset.py
kedro_datasets/pandas/__init__.py
kedro_datasets/pandas/csv_dataset.py
kedro_datasets/pandas/deltatable_dataset.py
kedro_datasets/pandas/excel_dataset.py
kedro_datasets-9.1.0.dist-info/METADATA
kedro_datasets-9.1.0.dist-info/WHEEL
kedro_datasets-9.1.0.dist-info/top_level.txt
kedro_datasets-9.1.0.dist-info/RECORD
